pyqt_highlight_completer/__init__.py
pyqt_highlight_completer/highlightCompleter.py
pyqt_highlight_completer-0.0.1.dist-info/LICENSE
pyqt_highlight_completer-0.0.1.dist-info/METADATA
pyqt_highlight_completer-0.0.1.dist-info/WHEEL
pyqt_highlight_completer-0.0.1.dist-info/top_level.txt
pyqt_highlight_completer-0.0.1.dist-info/RECORD
