Metadata-Version: 2.1
Name: pyqt-highlight-completer
Version: 0.0.1
Summary: PyQt highlight completer
Home-page: https://github.com/yjg30737/pyqt-highlight-completer.git
Author: Jung Gyu Yoon
Author-email: yjg30737@gmail.com
License: MIT
Platform: UNKNOWN
License-File: LICENSE
Requires-Dist: PyQt5 (>=5.8)
